ooga_booga_python/__init__.py
ooga_booga_python/asd.py
ooga_booga_python/client.py
ooga_booga_python/constants.py
ooga_booga_python/custom_logger.py
ooga_booga_python/exceptions.py
ooga_booga_python/http_client.py
ooga_booga_python/models.py
ooga_booga_python/scripts.py
ooga_booga_python-0.0.9.dist-info/licenses/LICENSE
ooga_booga_python-0.0.9.dist-info/METADATA
ooga_booga_python-0.0.9.dist-info/WHEEL
ooga_booga_python-0.0.9.dist-info/entry_points.txt
ooga_booga_python-0.0.9.dist-info/top_level.txt
ooga_booga_python-0.0.9.dist-info/RECORD
