Metadata-Version: 2.4
Name: Ooga-Booga-Python
Version: 0.0.9
Summary: A Python client for the Ooga Booga DEX aggregation and smart order routing REST API.
Author: Moritz
License: MIT License
Project-URL: Homepage, https://github.com/1220moritz/Ooga_Booga_Python
Project-URL: Bug Tracker, https://github.com/1220moritz/Ooga_Booga_Python/issues
Project-URL: Documentation, https://docs.oogabooga.io/
Keywords: ooga,booga,berachain,dex,api,client,web3,defi
Classifier: Programming Language :: Python :: 3
Classifier: Programming Language :: Python :: 3.9
Classifier: Programming Language :: Python :: 3.10
Classifier: Programming Language :: Python :: 3.11
Classifier: Programming Language :: Python :: 3.12
Classifier: License :: OSI Approved :: MIT License
Classifier: Operating System :: OS Independent
Classifier: Intended Audience :: Developers
Classifier: Topic :: Software Development :: Libraries :: Python Modules
Requires-Python: <4.0,>=3.9
License-File: LICENSE
Requires-Dist: aiohttp<4.0.0,>=3.12.13
Requires-Dist: pydantic<3.0.0,>=2.11.7
Requires-Dist: web3<8.0.0,>=7.12.0
Requires-Dist: eth-typing~=5.2.1
Requires-Dist: colorama~=0.4.6
Requires-Dist: python-dotenv~=1.1.0
Provides-Extra: dev
Requires-Dist: pytest<9.0.0,>=8.3.4; extra == "dev"
Requires-Dist: pytest-asyncio<1.0.0,>=0.24.0; extra == "dev"
Requires-Dist: ruff<1.0.0,>=0.1.0; extra == "dev"
Dynamic: license-file
